datadict_connector_base/__init__.py
datadict_connector_base/applier.py
datadict_connector_base/connector.py
datadict_connector_base/loader.py
datadict_connector_base/path_builder.py
datadict_connector_base/source.py
datadict_connector_base/types.py
datadict_connector_base/util.py
datadict_connector_base-0.0.2.dist-info/METADATA
datadict_connector_base-0.0.2.dist-info/WHEEL
datadict_connector_base-0.0.2.dist-info/top_level.txt
datadict_connector_base-0.0.2.dist-info/RECORD
